nunpy/__init__.py
nunpy/rechape.py
skmetpy-0.3.0.dist-info/METADATA
skmetpy-0.3.0.dist-info/WHEEL
skmetpy-0.3.0.dist-info/top_level.txt
skmetpy-0.3.0.dist-info/RECORD
