Metadata-Version: 2.1
Name: skmetpy
Version: 0.3.0
Summary: Descripción del paquete
Home-page: https://github.com/usuario/nombre_del_paquete
Author: Nombre Autor
Author-email: autor@gmail.com
License: UNKNOWN
Platform: UNKNOWN
